onegov.user-0.22.5-py3.6-nspkg.pth
onegov/user/.gitignore
onegov/user/__init__.py
onegov/user/cli.py
onegov/user/errors.py
onegov/user/integration.py
onegov/user/upgrade.py
onegov/user/utils.py
onegov/user/auth/__init__.py
onegov/user/auth/core.py
onegov/user/auth/provider.py
onegov/user/auth/second_factor.py
onegov/user/collections/__init__.py
onegov/user/collections/group.py
onegov/user/collections/user.py
onegov/user/forms/__init__.py
onegov/user/forms/group.py
onegov/user/forms/login.py
onegov/user/forms/registration.py
onegov/user/forms/reset_password.py
onegov/user/forms/signup_link.py
onegov/user/locale/de_ch/LC_MESSAGES/onegov.user.po
onegov/user/locale/fr_CH/LC_MESSAGES/onegov.user.po
onegov/user/locale/it_CH/LC_MESSAGES/onegov.user.po
onegov/user/locale/rm_CH/LC_MESSAGES/onegov.user.po
onegov/user/models/__init__.py
onegov/user/models/group.py
onegov/user/models/user.py
onegov/user/tests/test_auth.py
onegov/user/tests/test_cli.py
onegov/user/tests/test_collections.py
onegov/user/tests/test_forms.py
onegov/user/tests/test_integration.py
onegov/user/tests/test_models.py
onegov/user/tests/test_utils.py
onegov.user-0.22.5.dist-info/METADATA
onegov.user-0.22.5.dist-info/WHEEL
onegov.user-0.22.5.dist-info/entry_points.txt
onegov.user-0.22.5.dist-info/namespace_packages.txt
onegov.user-0.22.5.dist-info/top_level.txt
onegov.user-0.22.5.dist-info/RECORD
