Metadata-Version: 2.1
Name: onegov.user
Version: 0.22.5
Summary: A generic user model for OneGov.
Home-page: http://github.com/onegov/onegov.user
Author: Seantis GmbH
Author-email: info@seantis.ch
License: GPLv2
Platform: any
Classifier: Intended Audience :: Developers
Classifier: Programming Language :: Python :: 3 :: Only
Classifier: Programming Language :: Python :: 3.6
Classifier: Programming Language :: Python :: 3.7
Classifier: Topic :: Software Development :: Libraries :: Python Modules
Classifier: License :: OSI Approved :: GNU General Public License v2 (GPLv2)
Requires-Python: >=3.6
Requires-Dist: attrs
Requires-Dist: click
Requires-Dist: kerberos (>=1.3.0)
Requires-Dist: furl
Requires-Dist: itsdangerous
Requires-Dist: onegov.core (>=0.78.0)
Requires-Dist: onegov.form
Requires-Dist: sqlalchemy
Requires-Dist: ua-parser
Provides-Extra: test
Requires-Dist: coverage ; extra == 'test'
Requires-Dist: freezegun ; extra == 'test'
Requires-Dist: more.itsdangerous ; extra == 'test'
Requires-Dist: onegov-testing ; extra == 'test'
Requires-Dist: pyyaml ; extra == 'test'
Requires-Dist: webtest ; extra == 'test'
